pystocknow/__init__.py
pystocknow/sndata.py
pystocknow/sninsights.py
pystocknow-0.1.2.dist-info/licenses/LICENSE
pystocknow-0.1.2.dist-info/METADATA
pystocknow-0.1.2.dist-info/WHEEL
pystocknow-0.1.2.dist-info/top_level.txt
pystocknow-0.1.2.dist-info/RECORD
