Metadata-Version: 2.4
Name: pystocknow
Version: 0.1.2
Summary: Python programming interface for read StockNow platform marketing data and insights.
Author-email: StockNowAdmin <support@stocknow.xyz>
Project-URL: Homepage, https://github.com/ISTOCKNOW-Platform/stocknow-api-python-sdk
Project-URL: Bug Tracker, https://github.com/ISTOCKNOW-Platform/stocknow-api-python-sdk/issues
Keywords: StockNow,Data,Insights,Python API
Classifier: Programming Language :: Python :: 3
Classifier: License :: OSI Approved :: Apache Software License
Classifier: Operating System :: OS Independent
Requires-Python: >=3.7
License-File: LICENSE
Requires-Dist: requests
Dynamic: license-file
